hwamsmartctrl/__init__.py
hwamsmartctrl/airbox.py
hwamsmartctrl/stovedata.py
hwamsmartctrl-0.2.1.dist-info/LICENSE
hwamsmartctrl-0.2.1.dist-info/METADATA
hwamsmartctrl-0.2.1.dist-info/WHEEL
hwamsmartctrl-0.2.1.dist-info/top_level.txt
hwamsmartctrl-0.2.1.dist-info/RECORD
