Metadata-Version: 2.1
Name: hwamsmartctrl
Version: 0.2.1
Summary: Python API to interface HWAM® SmartControl™
Author-email: lordyavin <taa02kgvj@mozmail.com>
Project-URL: Homepage, https://github.com/lordyavin/hwam-smart-control
Project-URL: Issues, https://github.com/lordyavin/hwam-smart-control/issues
Classifier: Programming Language :: Python :: 3
Classifier: License :: OSI Approved :: MIT License
Classifier: Operating System :: OS Independent
Classifier: Development Status :: 3 - Alpha
Classifier: Intended Audience :: Developers
Classifier: Topic :: Home Automation
Requires-Python: >=3.8
License-File: LICENSE
Requires-Dist: aiohttp
Requires-Dist: aiodns
